fasttrackpy/__init__.py
fasttrackpy/cli.py
fasttrackpy/patterns/__init__.py
fasttrackpy/patterns/audio_textgrid.py
fasttrackpy/patterns/corpus.py
fasttrackpy/patterns/just_audio.py
fasttrackpy/processors/__init__.py
fasttrackpy/processors/aggs.py
fasttrackpy/processors/heuristic.py
fasttrackpy/processors/losses.py
fasttrackpy/processors/outputs.py
fasttrackpy/processors/smoothers.py
fasttrackpy/resources/config.yml
fasttrackpy/tracks.py
fasttrackpy/utils/__init__.py
fasttrackpy/utils/safely.py
fasttrackpy-0.5.4.dist-info/LICENSE
fasttrackpy-0.5.4.dist-info/METADATA
fasttrackpy-0.5.4.dist-info/WHEEL
fasttrackpy-0.5.4.dist-info/entry_points.txt
fasttrackpy-0.5.4.dist-info/RECORD
